RaiderFetch/__init__.py
RaiderFetch-1.0.dist-info/METADATA
RaiderFetch-1.0.dist-info/RECORD
RaiderFetch-1.0.dist-info/WHEEL
RaiderFetch-1.0.dist-info/top_level.txt
