Metadata-Version: 2.1
Name: RaiderFetch
Version: 1.0
Summary: A python3 library for getting information about the team
Home-page: https://github.com/frc5024/RaiderFetch
Author: Evan Pratten
Author-email: ewpratten@gmail.com
License: MIT
Platform: UNKNOWN
Classifier: Programming Language :: Python :: 3
Classifier: License :: OSI Approved :: MIT License
Classifier: Operating System :: OS Independent
Classifier: Development Status :: 5 - Production/Stable
Requires-Dist: requests
Requires-Dist: feedparser
